bisheng_ragas/__init__.py
bisheng_ragas/_analytics.py
bisheng_ragas/_version.py
bisheng_ragas/async_utils.py
bisheng_ragas/embeddings/__init__.py
bisheng_ragas/embeddings/base.py
bisheng_ragas/evaluation.py
bisheng_ragas/exceptions.py
bisheng_ragas/langchain/__init__.py
bisheng_ragas/langchain/evalchain.py
bisheng_ragas/langsmith/__init__.py
bisheng_ragas/langsmith/evaluator.py
bisheng_ragas/llama_index/__init__.py
bisheng_ragas/llama_index/evaluation.py
bisheng_ragas/llms/__init__.py
bisheng_ragas/llms/base.py
bisheng_ragas/llms/langchain.py
bisheng_ragas/llms/llamaindex.py
bisheng_ragas/llms/openai.py
bisheng_ragas/metrics/__init__.py
bisheng_ragas/metrics/_answer_correctness.py
bisheng_ragas/metrics/_answer_correctness_bisheng.py
bisheng_ragas/metrics/_answer_recall_bisheng.py
bisheng_ragas/metrics/_answer_relevance.py
bisheng_ragas/metrics/_answer_similarity.py
bisheng_ragas/metrics/_context_precision.py
bisheng_ragas/metrics/_context_recall.py
bisheng_ragas/metrics/_context_relevancy.py
bisheng_ragas/metrics/_faithfulness.py
bisheng_ragas/metrics/base.py
bisheng_ragas/metrics/critique.py
bisheng_ragas/testset/__init__.py
bisheng_ragas/testset/prompts.py
bisheng_ragas/testset/testset_generator.py
bisheng_ragas/testset/utils.py
bisheng_ragas/trainset/__init__.py
bisheng_ragas/trainset/prompts.py
bisheng_ragas/trainset/trainset_generator.py
bisheng_ragas/trainset/utils.py
bisheng_ragas/utils.py
bisheng_ragas/validation.py
bisheng_ragas_lc1-2.0.0.dist-info/METADATA
bisheng_ragas_lc1-2.0.0.dist-info/WHEEL
bisheng_ragas_lc1-2.0.0.dist-info/licenses/LICENSE
bisheng_ragas_lc1-2.0.0.dist-info/RECORD
